bio_embeddings_esm-0.2.1.data/data/source_docs/esm/CODE_OF_CONDUCT.rst
bio_embeddings_esm-0.2.1.data/data/source_docs/esm/LICENSE
bio_embeddings_esm-0.2.1.data/data/source_docs/esm/README.md
esm/__init__.py
esm/constants.py
esm/data.py
esm/model.py
esm/modules.py
esm/multihead_attention.py
esm/pretrained.py
esm/version.py
bio_embeddings_esm-0.2.1.dist-info/LICENSE
bio_embeddings_esm-0.2.1.dist-info/METADATA
bio_embeddings_esm-0.2.1.dist-info/WHEEL
bio_embeddings_esm-0.2.1.dist-info/top_level.txt
bio_embeddings_esm-0.2.1.dist-info/zip-safe
bio_embeddings_esm-0.2.1.dist-info/RECORD
